configdeck/__init__.py
configdeck/_compat.py
configdeck/_metadata.py
configdeck/deck.py
configdeck/parser.py
configdeck/schema.py
configdeck/app/__init__.py
configdeck/app/base.py
configdeck/app/plugin.py
configdeck/contrib/__init__.py
configdeck/contrib/schema/__init__.py
configdeck/contrib/schema/devserver.py
configdeck/contrib/schema/django_jenkins.py
configdeck/contrib/schema/django_openid_auth.py
configdeck/contrib/schema/nexus.py
configdeck/contrib/schema/preflight.py
configdeck/contrib/schema/pystatsd.py
configdeck/contrib/schema/raven.py
configdeck/contrib/schema/saml2idp.py
configdeck/inischema/__init__.py
configdeck/inischema/attributed.py
configdeck/inischema/deck.py
configdeck/inischema/parsers.py
configdeck/inischema/typed.py
configdeck/tests/__init__.py
configdeck/tests/test_contrib_schema.py
configdeck/tests/test_metadata.py
configdeck/tests/test_parser.py
configdeck/tests/test_schema.py
configdeck/tests/test_schemaconfig.py
configdeck/tests/app/__init__.py
configdeck/tests/app/test_base.py
configdeck/tests/app/test_plugin.py
configdeck/tests/inischema/__init__.py
configdeck/tests/inischema/test_attributed.py
configdeck/tests/inischema/test_deck.py
configdeck/tests/inischema/test_deck2deck.py
configdeck/tests/inischema/test_parsers.py
configdeck/tests/inischema/test_typed.py
configdeck-1.2.1.dist-info/DESCRIPTION.rst
configdeck-1.2.1.dist-info/METADATA
configdeck-1.2.1.dist-info/RECORD
configdeck-1.2.1.dist-info/WHEEL
configdeck-1.2.1.dist-info/dependency_links.txt
configdeck-1.2.1.dist-info/metadata.json
configdeck-1.2.1.dist-info/top_level.txt
configdeck-1.2.1.dist-info/zip-safe
